pytest_parawtf.py
pytest_parawtf-1.0.2.dist-info/LICENSE.txt
pytest_parawtf-1.0.2.dist-info/METADATA
pytest_parawtf-1.0.2.dist-info/RECORD
pytest_parawtf-1.0.2.dist-info/WHEEL
pytest_parawtf-1.0.2.dist-info/entry_points.txt
pytest_parawtf-1.0.2.dist-info/top_level.txt
