Metadata-Version: 2.1
Name: pytest-parawtf
Version: 1.0.2
Summary: Finally spell paramete?ri[sz]e correctly
Home-page: https://bitbucket.org/flub/pytest-parawtf
Author: Floris Bruynooghe
Author-email: flub@devork.be
License: MIT
Keywords: pytest parametrise parametrize parameterise parameterize params
Platform: unix
Platform: linux
Platform: osx
Platform: cygwin
Platform: win32
Classifier: Development Status :: 4 - Beta
Classifier: Environment :: Console
Classifier: Environment :: Plugins
Classifier: Framework :: Pytest
Classifier: Intended Audience :: Developers
Classifier: License :: DFSG approved
Classifier: License :: OSI Approved :: MIT License
Classifier: Operating System :: OS Independent
Classifier: Programming Language :: Python
Classifier: Programming Language :: Python :: 2
Classifier: Programming Language :: Python :: 2.7
Classifier: Programming Language :: Python :: 3
Classifier: Programming Language :: Python :: 3.4
Classifier: Programming Language :: Python :: 3.5
Classifier: Programming Language :: Python :: 3.6
Classifier: Programming Language :: Python :: 3.7
Classifier: Topic :: Software Development :: Testing
Requires-Dist: pytest (>=3.6.0)
